bin/__init__.py
bin/nonce/__init__.py
bin/nonce/deco_zst.py
bin/nonce/simple_colored_gui.py
bin/nonce/simple_gui.py
pazgui/__init__.py
pazgui/accessories.py
pazgui/behavior.py
pazgui/behaviour.py
pazgui/characters.py
pazgui/gui.py
pazgui/keycodes.py
pazgui/paz_behaviour.py
pazgui/pazgui.py
tests/__init__.py
tests/basic_guis.py
tests/test_auto.py
tests/test_manual.py
pazgui-0.0.1.dist-info/LICENSE
pazgui-0.0.1.dist-info/METADATA
pazgui-0.0.1.dist-info/WHEEL
pazgui-0.0.1.dist-info/top_level.txt
pazgui-0.0.1.dist-info/RECORD
