Metadata-Version: 2.1
Name: pazgui
Version: 0.0.1
Summary: Python terminal GUI toolkit
Home-page: https://github.com/dmrokan/pazgui
Author: Okan Demir
Author-email: okndemir@gmail.com
License: UNKNOWN
Platform: UNKNOWN
Classifier: Programming Language :: Python :: 3
Classifier: License :: OSI Approved :: MIT License
Requires-Python: >=3.8
Requires-Dist: blessed
Requires-Dist: schedule
